easy_excel
