Metadata-Version: 1.0
Name: easy-excel
Version: 0.0.7
Summary: Python create excel
Home-page: https://github.com/Nick1994209/python_easy_excel/
Author: nick1994209
Author-email: nick1994209@gmail.com
License: MIT
Platform: UNKNOWN
